Metadata-Version: 1.0
Name: guacapyClientRest
Version: 0.0.1
Summary: Python REST API client for Guacamole 0.9.13 version
Home-page: https://github.com/feifeixj/guacamole-client-rest-pyhton
Author: feifeixj
Author-email: 15851862881@163.com
License: UNKNOWN
Platform: UNKNOWN
